shansort.cp311-win32.pyd
shansort-0.1.5.dist-info/licenses/LICENSE
shansort-0.1.5.dist-info/METADATA
shansort-0.1.5.dist-info/WHEEL
shansort-0.1.5.dist-info/top_level.txt
shansort-0.1.5.dist-info/RECORD
