Metadata-Version: 2.4
Name: shansort
Version: 0.1.5
Summary: Unified fast radix sort for int, float, and string
Author: Bhavani Shanker
Author-email: bhavanishanker9@proton.me
Classifier: Programming Language :: Python :: 3
Classifier: Programming Language :: C++
Classifier: License :: OSI Approved :: MIT License
Classifier: Operating System :: OS Independent
Requires-Python: >=3.8
License-File: LICENSE
Requires-Dist: pybind11>=2.6.0
Dynamic: author
Dynamic: author-email
Dynamic: classifier
Dynamic: description
Dynamic: description-content-type
Dynamic: license-file
Dynamic: requires-dist
Dynamic: requires-python
Dynamic: summary
